libTWLPy/__init__.py
libTWLPy/commonkeys.py
libTWLPy/content.py
libTWLPy/crypto.py
libTWLPy/nus.py
libTWLPy/shared.py
libTWLPy/tad.py
libTWLPy/ticket.py
libTWLPy/title.py
libTWLPy/tmd.py
libTWLPy/types.py
libTWLPy-0.1.0.dist-info/LICENSE
libTWLPy-0.1.0.dist-info/METADATA
libTWLPy-0.1.0.dist-info/WHEEL
libTWLPy-0.1.0.dist-info/top_level.txt
libTWLPy-0.1.0.dist-info/RECORD
