Metadata-Version: 2.1
Name: libTWLPy
Version: 0.1.0
Summary: A modern Python library for handling files and formats used by the DSi.
Author-email: NinjaCheetah <ninjacheetah@ncxprogramming.com>, Lillian Skinner <lillian@randommeaninglesscharacters.com>
Project-URL: Homepage, https://github.com/NinjaCheetah/libTWLPy
Project-URL: Issues, https://github.com/NinjaCheetah/libTWLPy/issues
Classifier: Programming Language :: Python :: 3
Classifier: License :: OSI Approved :: MIT License
Classifier: Operating System :: OS Independent
Requires-Python: >=3.10
License-File: LICENSE
Requires-Dist: pycryptodome
Requires-Dist: requests
